LICENSE
MANIFEST.in
README.rst
setup.py
django_e1337cms.egg-info/PKG-INFO
django_e1337cms.egg-info/SOURCES.txt
django_e1337cms.egg-info/dependency_links.txt
django_e1337cms.egg-info/not-zip-safe
django_e1337cms.egg-info/requires.txt
django_e1337cms.egg-info/top_level.txt
e1337cms/__init__.py
e1337cms/admin.py
e1337cms/models.py
e1337cms/settings.py
e1337cms/tests.py
e1337cms/urls.py
e1337cms/views.py
e1337cms/migrations/0001_initial.py
e1337cms/migrations/__init__.py
e1337cms/templatetags/__init__.py
e1337cms/templatetags/e1337tags.py