Metadata-Version: 1.0
Name: django-e1337cms
Version: 0.0.3
Summary: Simple and Lightweight but Powerful and Open Source CMS only for e1337 people.
Home-page: https://bitbucket.org/DNX/django-e1337cms/
Author: Denis Darii
Author-email: denis.darii@gmail.com
License: BSD License
Platform: UNKNOWN
Classifier: Framework :: Django
Classifier: Programming Language :: Python
Classifier: Development Status :: 3 - Alpha
Classifier: Intended Audience :: Developers
Classifier: Operating System :: OS Independent
Classifier: License :: OSI Approved :: BSD License
Classifier: Environment :: Web Environment
Classifier: Topic :: Internet :: WWW/HTTP :: Dynamic Content
Classifier: Topic :: Software Development :: Libraries :: Python Modules
Classifier: Topic :: Software Development :: Libraries :: Application Frameworks
